genlab_ai_game_util/RedisBaseCommand.py
genlab_ai_game_util/RedisClient.py
genlab_ai_game_util/__init__.py
genlab_ai_game_util/process.py
genlab_ai_game_util-0.0.31.dist-info/LICENSE
genlab_ai_game_util-0.0.31.dist-info/METADATA
genlab_ai_game_util-0.0.31.dist-info/WHEEL
genlab_ai_game_util-0.0.31.dist-info/top_level.txt
genlab_ai_game_util-0.0.31.dist-info/RECORD
